apm/__init__.py
apm/__pkginfo__.py
apm/_util.py
apm/agg.py
apm/case_of.py
apm/core.py
apm/error.py
apm/generic.py
apm/guarded.py
apm/match.py
apm/no_value.py
apm/overload.py
apm/patterns.py
apm/try_match.py
apm/typefoo.py
tests/__init__.py
tests/test_agg.py
tests/test_basic_usecases.py
tests/test_capture.py
tests/test_case_distinction.py
tests/test_case_of.py
tests/test_compat.py
tests/test_core.py
tests/test_dict.py
tests/test_exceptions.py
tests/test_generic.py
tests/test_guarded.py
tests/test_hash.py
tests/test_issues.py
tests/test_object.py
tests/test_parameters.py
tests/test_readme.py
tests/test_reporting.py
tests/test_some.py
tests/test_string.py
tests/test_terse_style.py
tests/test_transform.py
tests/test_try_match.py
tests/test_typefoo.py
tests/test_unhappy_cases.py
tests/test_util.py
awesome_pattern_matching-0.24.4.dist-info/LICENSE
awesome_pattern_matching-0.24.4.dist-info/METADATA
awesome_pattern_matching-0.24.4.dist-info/WHEEL
awesome_pattern_matching-0.24.4.dist-info/top_level.txt
awesome_pattern_matching-0.24.4.dist-info/RECORD
