Metadata-Version: 2.1
Name: awesome-pattern-matching
Version: 0.24.4
Summary: Awesome Pattern Matching
Home-page: https://github.com/scravy/awesome-pattern-matching
Author: Julian Fleischer
Author-email: tirednesscankill@warhog.net
License: UNKNOWN
Platform: UNKNOWN
Classifier: Programming Language :: Python :: 3
Classifier: License :: OSI Approved :: MIT License
Classifier: Operating System :: OS Independent
Requires-Python: >=3.7
